sawpit/__init__.py
sawpit/rest_request.py
sawpit/utils.py
sawpit/ws_message.py
sawpit/ws_response.py
sawpit/ws_test.py
sawpit/ws_timeout_error.py
sawpit-0.0.1.dist-info/LICENSE
sawpit-0.0.1.dist-info/METADATA
sawpit-0.0.1.dist-info/WHEEL
sawpit-0.0.1.dist-info/top_level.txt
sawpit-0.0.1.dist-info/RECORD
