Metadata-Version: 2.1
Name: sawpit
Version: 0.0.1
Summary: Work in progress fork of pywsitest
Home-page: https://github.com/jamsidedown/sawpit
Author: Rob Anderson
Author-email: opensource@robanderson.dev
License: MIT
Keywords: websocket integration test testing
Platform: UNKNOWN
Classifier: Intended Audience :: Developers
Classifier: Development Status :: 3 - Alpha
Classifier: Programming Language :: Python :: 3
Classifier: License :: OSI Approved :: MIT License
Classifier: Operating System :: OS Independent
Classifier: Natural Language :: English
Requires-Python: >=3.7
Requires-Dist: websockets
Requires-Dist: requests
